Lab 2/16CO104-VG2.v
module segment_7_display(in, a, b, c, d, e, f, g);

	input [3:0]in;
	output a, b, c, d, e, f, g;
	wire a3, a2, a1, a0, a3_, a2_, a1_, a0_;
	wire t1, t2, t3, t4, t5, t6, t7, t8, t9;
	wire p,q,r,s,t,w1,w2,w3,w4;

	or(a3, in[3], 0);
	or(a2, in[2], 0);
	or(a1, in[1], 0);
	or(a0, in[0], 0);
	
	not(a0_, in[0]);
	not(a1_, in[1]);
	not(a2_, in[2]);
	not(a3_, in[3]);
	
	and(t1, a0_, a1_);
	or(t2, a1_, a0_);
	and(t3, a2, t2);
	or(a, a3, t3, t1);
	
	and(t4, a2_, a0_);
	and(t5, a2, a0);
	or(b, t4, t5, a3, a1);
	
	and(p,a1,a0_);
	and(q,a1,a2_);
	and(r,a0_,a2_);
	and(s,a0,a2,a1_);
	or(e,p,q,r,s,a3);


	or(f,p,r);

	xor(t,a1, a2);
	or(g,a3,p,t);

	or(d,a3,a2,a1_,a0);

	and(w1,a1,a0);
	and(w2,a1_,a0_);
	and(w3,a3_,a2_);
	or(c,a3,w1,w2,w3);
	
endmodule

Lab 2/16CO104-V2.v
`timescale 1ns/1ps

module test;

	reg [3:0]in;
	wire a, b, c, d, e, f, g;
	
	segment_7_display segment_7(in, a, b, c, d, e, f, g);
	
	initial begin
		$dumpfile("16CO104-V2.vcd");
		$dumpvars(0, test);
		
		in=4'b0000;
		#10 in=4'b0001;
		#10 in=4'b0010;
		#10 in=4'b0011;
		#10 in=4'b0100;
		#10 in=4'b0101;
		#10 in=4'b0110;
		#10 in=4'b0111;
		#10 in=4'b1000;
		#10 in=4'b1001;
		
	end
	
	initial
		$monitor("INPUT = %b, a=%b, b=%b, c=%b, d=%b, e=%b, f=%b, g=%b", in, a, b, c, d, e, f, g);
	
	initial #100 $finish;

endmodule

Lab Programs/Lab 2/16CO104-V2.vcd
$date
	Thu Oct  5 16:15:48 2017
$end
$version
	Icarus Verilog
$end
$timescale
	1ps
$end
$scope module test $end
$var wire 1 ! g $end
$var wire 1 " f $end
$var wire 1 # e $end
$var wire 1 $ d $end
$var wire 1 % c $end
$var wire 1 & b $end
$var wire 1 ' a $end
$var reg 4 ( in [3:0] $end
$scope module segment_7 $end
$var wire 1 ' a $end
$var wire 1 ) a0 $end
$var wire 1 * a0_ $end
$var wire 1 + a1 $end
$var wire 1 , a1_ $end
$var wire 1 - a2 $end
$var wire 1 . a2_ $end
$var wire 1 / a3 $end
$var wire 1 0 a3_ $end
$var wire 1 & b $end
$var wire 1 % c $end
$var wire 1 $ d $end
$var wire 1 # e $end
$var wire 1 " f $end
$var wire 1 ! g $end
$var wire 4 1 in [3:0] $end
$var wire 1 2 p $end
$var wire 1 3 q $end
$var wire 1 4 r $end
$var wire 1 5 s $end
$var wire 1 6 t $end
$var wire 1 7 t1 $end
$var wire 1 8 t2 $end
$var wire 1 9 t3 $end
$var wire 1 : t4 $end
$var wire 1 ; t5 $end
$var wire 1 < w1 $end
$var wire 1 = w2 $end
$var wire 1 > w3 $end
$upscope $end
$upscope $end
$enddefinitions $end
#0
$dumpvars
1>
1=
0<
0;
1:
09
18
17
06
05
14
03
02
b0 1
10
0/
1.
0-
1,
0+
1*
0)
b0 (
1'
1&
1%
1$
1#
1"
0!
$end
#10000
0#
0'
0&
0"
07
0:
04
0=
1)
0*
b1 (
b1 1
#20000
1#
1!
1"
1&
13
16
1:
12
14
0$
1+
0)
1*
0,
b10 (
b10 1
#30000
0"
1$
1<
08
0:
02
04
1)
0*
b11 (
b11 1
#40000
0#
1'
19
0&
0<
17
18
1=
03
0>
1-
0+
0)
1*
1,
0.
b100 (
b100 1
#50000
1#
1&
0%
1;
15
07
0=
1)
0*
b101 (
b101 1
#60000
1"
06
0;
12
05
1+
0)
1*
0,
b110 (
b110 1
#70000
0'
0#
1%
09
0"
0!
1;
1<
08
02
1)
0*
b111 (
b111 1
#80000
1#
1"
1'
1!
0;
0<
17
18
1=
1:
14
1/
0-
0+
0)
1*
1,
1.
00
b1000 (
b1000 1
#90000
0"
07
0:
04
0=
1)
0*
b1001 (
b1001 1
