Lab Programs/Lab 5/16CO104-VD5.v
module siso_register_4bit(
	input in,
	input clk,
	output [0:3] out,
	input rst
);

	D_FF d1(clk, in, out[0], rst);
	D_FF d2(clk, out[0], out[1], rst);
	D_FF d3(clk, out[1], out[2], rst);
	D_FF d4(clk, out[2], out[3], rst);

endmodule


module D_FF(
	input clk,
	input d,
	output reg q,
	input rst
);

	always @(posedge clk) begin
		q = (~rst)&d;
	end

endmodule

Lab Programs/Lab 5/16CO104-V5.v
`timescale 1ns/1ps

module tb_siso_register_4bit;

	reg in;
	reg clk;
	output [3:0] out;
	reg rst;
	
	siso_register_4bit siso4bit(in, clk, out, rst);
	
	//Clock
	initial begin
		clk = 1'b1;
		repeat(100)
		#10 clk = ~clk;
	end
	
	initial begin
	
		$dumpfile("16CO104-V5.vcd");
		$dumpvars(0, tb_siso_register_4bit);
		$monitor("INPUT = %b, OUTPUT = %b", in, out);
		
		in = 1'b0;
		rst = 1'b1;
		
		#20;
		rst = 1'b0;
		in = 1'b1;
		
		#20;
		in = 1'b0;
		
		#20;
		in = 1'b1;
		
		#20;
		in = 1'b0;

		#20;
		in = 1'b0;

		#20;
		in = 1'b1;
		
		#20 $finish;
	end

endmodule

Lab Programs/Lab 5/16CO104-V5.vcd
$date
	Sat Nov  4 13:37:54 2017
$end
$version
	Icarus Verilog
$end
$timescale
	1ps
$end
$scope module tb_siso_register_4bit $end
$var wire 4 ! out [3:0] $end
$var reg 1 " clk $end
$var reg 1 # in $end
$var reg 1 $ rst $end
$scope module siso4bit $end
$var wire 1 % clk $end
$var wire 1 & in $end
$var wire 4 ' out [0:3] $end
$var wire 1 ( rst $end
$scope module d1 $end
$var wire 1 % clk $end
$var wire 1 & d $end
$var wire 1 ( rst $end
$var reg 1 ) q $end
$upscope $end
$scope module d2 $end
$var wire 1 % clk $end
$var wire 1 * d $end
$var wire 1 ( rst $end
$var reg 1 + q $end
$upscope $end
$scope module d3 $end
$var wire 1 % clk $end
$var wire 1 , d $end
$var wire 1 ( rst $end
$var reg 1 - q $end
$upscope $end
$scope module d4 $end
$var wire 1 % clk $end
$var wire 1 . d $end
$var wire 1 ( rst $end
$var reg 1 / q $end
$upscope $end
$upscope $end
$upscope $end
$enddefinitions $end
#0
$dumpvars
0/
0.
0-
0,
0+
0*
0)
1(
b0 '
0&
1%
1$
0#
1"
b0 !
$end
#7000
0"
0%
#14000
1"
1%
#20000
1#
1&
0$
0(
#21000
0"
0%
#28000
1*
1)
b1000 !
b1000 '
1"
1%
#35000
0"
0%
#40000
0#
0&
#42000
1,
0*
1+
0)
b100 !
b100 '
1"
1%
#49000
0"
0%
#56000
0,
1.
0+
1-
b10 !
b10 '
1"
1%
#60000
1#
1&
#63000
0"
0%
#70000
0.
1*
1/
0-
1)
b1001 !
b1001 '
1"
1%
#77000
0"
0%
#80000
0#
0&
#84000
0*
1,
0)
1+
0/
b100 !
b100 '
1"
1%
#91000
0"
0%
#98000
1.
0,
1-
0+
b10 !
b10 '
1"
1%
#105000
0"
0%
#112000
0.
0-
1/
b1 !
b1 '
1"
1%
#119000
0"
0%
#120000
1#
1&
#126000
1*
0/
1)
b1000 !
b1000 '
1"
1%
#133000
0"
0%
#140000
1,
1+
b1100 !
b1100 '
1"
1%
