Lab Programs/Lab 4/16CO104-VG4.v
module parallel_register_4bit(
	input [3:0] in,
	input clk,
	output [3:0] out
);

	D_FF d1(clk, in[0], out[0]);
	D_FF d2(clk, in[1], out[1]);
	D_FF d3(clk, in[2], out[2]);
	D_FF d4(clk, in[3], out[3]);

endmodule

module D_FF(
	input clk,
	input d,
	output q
);

	and a1(q, d, 1);

endmodule

Lab Programs/Lab 4/16CO104-V4.v
`timescale 1ns/1ps

module tb_parallel_register_4bit;

	reg [3:0] in;
	reg clk;
	output [3:0] out;
	
	parallel_register_4bit pr4bit(in, clk, out);
	
	//Clock
	initial begin
		clk = 1'b1;
		repeat(100)
		#10 clk = ~clk;
	end
	
	initial begin
	
		$dumpfile("16CO104-V4.vcd");
		$dumpvars(0, tb_parallel_register_4bit);
		$monitor("INPUT = %b, OUTPUT = %b", in, out);
		
		in = 4'b0000;
		
		#20;
		in = 4'b0101;
		
		#20;
		in = 4'b0110;
		
		#20;
		in = 4'b1010;
		
		#20;
		in = 4'b1111;
		
		#20 $finish;
	end

endmodule

Lab Programs/Lab 4/16CO104-V4.vcd
$date
	Thu Nov  2 15:56:39 2017
$end
$version
	Icarus Verilog
$end
$timescale
	1ps
$end
$scope module tb_parallel_register_4bit $end
$var wire 4 ! out [3:0] $end
$var reg 1 " clk $end
$var reg 4 # in [3:0] $end
$scope module pr4bit $end
$var wire 1 $ clk $end
$var wire 4 % in [3:0] $end
$var wire 4 & out [3:0] $end
$scope module d1 $end
$var wire 1 $ clk $end
$var wire 1 ' d $end
$var reg 1 ( q $end
$upscope $end
$scope module d2 $end
$var wire 1 $ clk $end
$var wire 1 ) d $end
$var reg 1 * q $end
$upscope $end
$scope module d3 $end
$var wire 1 $ clk $end
$var wire 1 + d $end
$var reg 1 , q $end
$upscope $end
$scope module d4 $end
$var wire 1 $ clk $end
$var wire 1 - d $end
$var reg 1 . q $end
$upscope $end
$upscope $end
$upscope $end
$enddefinitions $end
#0
$dumpvars
0.
0-
0,
0+
0*
0)
0(
0'
b0 &
b0 %
1$
b0 #
1"
b0 !
$end
#7000
0"
0$
#14000
1"
1$
#20000
1'
1+
b101 #
b101 %
#21000
0"
0$
#28000
1(
1,
b101 !
b101 &
1"
1$
#35000
0"
0$
#40000
0'
1)
b110 #
b110 %
#42000
1*
0(
b110 !
b110 &
1"
1$
#49000
0"
0$
#56000
1"
1$
#60000
0+
1-
b1010 #
b1010 %
#63000
0"
0$
#70000
1.
0,
b1010 !
b1010 &
1"
1$
#77000
0"
0$
#80000
1'
1+
b1111 #
b1111 %
#84000
1(
1,
b1111 !
b1111 &
1"
1$
