Car Light Controller (Mini Project)/Verilog/VerilogDM-104-148.v
/*  CAR LIGHT CONTROLLER
	REG NO :			16CO104
						16CO148

	ABSTRACT :			This mini-project is a car light controller which controls all the interior and exterior lights of the car based on the inputs
						at the various switches. The main switch , door switches and the key switch are responsible for the output of the interior light.
						The exterior lights can be controlled using the select lines of the multiplexers.

	FUNCTIONALITIES :	The interior light has the following functionalities :-
							ON
							OFF
							DOOR

						The exterior light has the following functionalities :-
							OFF
							LEFT INDICATOR
							RIGHT INDICATOR
							BREAKDOWN INDICATOR	

	DESCRIPTION OF CODE :	This dataflow modelling makes a demux and a mux and uses them to control the outputs of the internal and the external lights.



*/



module demux_1x4 (
	output [3:0] out,		// demux output
	input in, 				// demux input
	input [0:1] select 		// select lines
);
	output [0:1] select_; 	// complement of select lines

	assign
		select_[0] = ~select[0],
		select_[1] = ~select[1],

		out[0] = in & select_[0] & select_[1],
		out[1] = in & select_[0] & select[1],
		out[2] = in & select[0] & select_[1],
		out[3] = in & select[0] & select[1];

endmodule


module mux_4x1 (
	output out,				// mux output
	input [3:0] in, 		// mux input 
	input [0:1] select 		// select lines
);
	output [3:0] temp; 		// temporary variable
	output [0:1] select_; 	// complement of select lines

	assign
		select_[0] = ~select[0],
		select_[1] = ~select[1],

		temp[0] = in[0] & select_[0] & select_[1],
		temp[1] = in[1] & select_[0] & select[1],
		temp[2] = in[2] & select[0] & select_[1],
		temp[3] = in[3] & select[0] & select[1],

		out = temp[0] | temp[1] | temp[2] | temp[3]; 

endmodule


module internal_lights (
	output light, 			// internal light
	input key, 				// key switch
	input [0:3] door,		// door switches
	input [0:1] select 		// select lines
);

	output [3:0]mux_in;

	assign
		mux_in[1] = door[0] | door[1] | door[2] | door[3] | key,

		mux_in[0] = 1,
		mux_in[2] = 0,
		mux_in[3] = 0;

	mux_4x1 mux(light, mux_in, select);

endmodule


module external_lights (
	output light_left,		//left indicator
	output light_right,		//right indicator
	input [0:1] select,		//select lines
	input clk				//clock pulse
);

	output [3:0] temp;
	output [3:0] mux_in1;
	output [3:0] mux_in2;
	output t1, t2;

	demux_1x4 demux(temp, 1, select);

	//MUX1
	assign
		mux_in1[0] = ~temp[0],
		mux_in1[1] = ~temp[1],

		mux_in1[2] = temp[2],
		mux_in1[3] = temp[3];

	//MUX2
	assign
		mux_in2[0] = ~temp[0],
		mux_in2[2] = ~temp[2],

		mux_in2[1] = temp[1],
		mux_in2[3] = temp[3];

	//External Lights
	mux_4x1 mux1(t1, mux_in1, select);
	mux_4x1 mux2(t2, mux_in2, select);

	assign
		light_left = clk & t1,
		light_right = clk & t2;

endmodule


module VerilogGM_104_148(
	output light,				// internal light
	input key, 					// key switches
	input [0:3] door,			// door switches
	input [0:1] select_int,		// select lines

	output light_left,			// left indicator
	output light_right,			// right indicator
	input [0:1] select_ext,		// controls
	input clk 					// clock pulse
);

	internal_lights int_light(light, key, door, select_int);
	external_lights ext_light(light_left, light_right, select_ext, clk);

endmodule

Car Light Controller (Mini Project)/Verilog/Verilog-104-148 .v
/*  CAR LIGHT CONTROLLER
	REG NO :			16CO104
						16CO148

	ABSTRACT :			This mini-project is a car light controller which controls all the interior and exterior lights of the car based on the inputs
						at the various switches. The main switch , door switches and the key switch are responsible for the output of the interior light.
						The exterior lights can be controlled using the select lines of the multiplexers.

	FUNCTIONALITIES :	The interior light has the following functionalities :-
							ON
							OFF
							DOOR

						The exterior light has the following functionalities :-
							OFF
							LEFT INDICATOR
							RIGHT INDICATOR
							BREAKDOWN INDICATOR	

	DESCRIPTION OF CODE :	This is the test bench which provides the stimulus to the main module .
							The door input controls the door switches , key input controls the key switches ,
							select_int controls the main switch and select_ext controls the external light
							controls .



*/





`timescale 1ns/1ps

module Verilog_104_148;

	//Internal Lights
	reg [0:3] door;				// door switches
	reg key;					// key switch
	reg [0:1] select_int;		// main switch
	output internal_light;		// internal light

	//External Lights
	output light_left;			// left indicator
	output light_right;			// right indicator
	reg [0:1] select_ext;		// control
	reg clk;					// clock pulse


	VerilogGM_104_148 car_lights(internal_light, key, door, select_int, 
		light_left, light_right, select_ext, clk);

	//Clock
	initial begin
		clk = 1'b1;
		repeat(100)
		#5 clk = ~clk;
	end

	initial begin

		$dumpfile("VerilogBM-104-148.vcd");
		$dumpvars(0, Verilog_104_148);
		$display("\nDoor\tSelect\t\tKey\tInternal Light\t\tSelect\t\tExternal Left Indicator\t\tExternal Right Indicator\t\n");

		door = 4'b0000;
		key = 0;
		select_int = 2'b00;
		select_ext = 2'b00;

		#40;
		door = 4'b0100;
		key = 0;
		select_int = 2'b01;
		select_ext = 2'b01;

		#40;
		door = 4'b0000;
		key = 0;
		select_int = 2'b01;	
		select_ext = 2'b10;				

		#40;
		door = 4'b0000;
		key = 1;
		select_int = 2'b01;
		select_ext = 2'b00;

		#40;
		door = 4'b0101;
		key = 1;
		select_int = 2'b11;
		select_ext = 2'b11;

		#40 $finish;
	end

	//Monitor Statements
	initial
		$monitor("%b\t%b\t\t%b\t%b\t\t\t%b\t\t%b\t\t\t\t%b", 
			door, select_int, key, internal_light, select_ext, light_left, light_right);


endmodule

Car Light Controller (Mini Project)/Verilog/VerilogDM-104-148.vcd
$date
	Sun Nov  5 15:54:58 2017
$end
$version
	Icarus Verilog
$end
$timescale
	1ps
$end
$scope module Verilog_104_148 $end
$var wire 1 ! internal_light $end
$var wire 1 " light_left $end
$var wire 1 # light_right $end
$var reg 1 $ clk $end
$var reg 4 % door [0:3] $end
$var reg 1 & key $end
$var reg 2 ' select_ext [0:1] $end
$var reg 2 ( select_int [0:1] $end
$scope module car_lights $end
$var wire 1 ) clk $end
$var wire 4 * door [0:3] $end
$var wire 1 + key $end
$var wire 1 ! light $end
$var wire 1 " light_left $end
$var wire 1 # light_right $end
$var wire 2 , select_ext [0:1] $end
$var wire 2 - select_int [0:1] $end
$scope module int_light $end
$var wire 4 . door [0:3] $end
$var wire 1 + key $end
$var wire 1 ! light $end
$var wire 4 / mux_in [3:0] $end
$var wire 2 0 select [0:1] $end
$scope module mux $end
$var wire 4 1 in [3:0] $end
$var wire 1 ! out $end
$var wire 2 2 select [0:1] $end
$var wire 2 3 select_ [0:1] $end
$var wire 4 4 temp [3:0] $end
$upscope $end
$upscope $end
$scope module ext_light $end
$var wire 1 ) clk $end
$var wire 1 " light_left $end
$var wire 1 # light_right $end
$var wire 4 5 mux_in1 [3:0] $end
$var wire 4 6 mux_in2 [3:0] $end
$var wire 2 7 select [0:1] $end
$var wire 1 8 t1 $end
$var wire 1 9 t2 $end
$var wire 4 : temp [3:0] $end
$scope module demux $end
$var wire 1 ; in $end
$var wire 4 < out [3:0] $end
$var wire 2 = select [0:1] $end
$var wire 2 > select_ [0:1] $end
$upscope $end
$scope module mux1 $end
$var wire 4 ? in [3:0] $end
$var wire 1 8 out $end
$var wire 2 @ select [0:1] $end
$var wire 2 A select_ [0:1] $end
$var wire 4 B temp [3:0] $end
$upscope $end
$scope module mux2 $end
$var wire 4 C in [3:0] $end
$var wire 1 9 out $end
$var wire 2 D select [0:1] $end
$var wire 2 E select_ [0:1] $end
$var wire 4 F temp [3:0] $end
$upscope $end
$upscope $end
$upscope $end
$upscope $end
$enddefinitions $end
#0
$dumpvars
b0 F
b11 E
b0 D
b100 C
b0 B
b11 A
b0 @
b10 ?
b11 >
b0 =
b1 <
1;
b1 :
09
08
b0 7
b100 6
b10 5
b1 4
b11 3
b0 2
b1 1
b0 0
b1 /
b0 .
b0 -
b0 ,
0+
b0 *
1)
b0 (
b0 '
0&
b0 %
1$
0#
0"
1!
$end
#5000
0$
0)
#10000
1$
1)
#15000
0$
0)
#20000
1$
1)
#25000
0$
0)
#30000
1$
1)
#35000
0$
0)
#40000
1#
19
1!
0"
b10 F
08
b11 /
b11 1
b1 5
b1 ?
b10 4
b111 6
b111 C
b10 >
b10 :
b10 <
b10 A
b0 B
b10 E
b10 3
1$
1)
b1 '
b1 ,
b1 7
b1 =
b1 @
b1 D
b1 (
b1 -
b1 0
b1 2
b100 %
b100 *
b100 .
#45000
0#
0$
0)
#50000
1#
1$
1)
#55000
0#
0$
0)
#60000
1#
1$
1)
#65000
0#
0$
0)
#70000
1#
1$
1)
#75000
0#
0$
0)
#80000
0!
1"
18
b0 4
09
b1 /
b1 1
b111 5
b111 ?
b100 B
b1 6
b1 C
b1 >
b100 :
b100 <
b1 A
b1 E
b0 F
0#
1$
1)
b10 '
b10 ,
b10 7
b10 =
b10 @
b10 D
b0 %
b0 *
b0 .
#85000
0"
0$
0)
#90000
1"
1$
1)
#95000
0"
0$
0)
#100000
1"
1$
1)
#105000
0"
0$
0)
#110000
1"
1$
1)
#115000
0"
0$
0)
#120000
0#
09
1!
08
b100 6
b100 C
b0 F
b10 5
b10 ?
b10 4
b1 :
b1 <
b0 B
b11 >
b11 A
b11 E
0"
b11 /
b11 1
1$
1)
b0 '
b0 ,
b0 7
b0 =
b0 @
b0 D
1&
1+
#125000
0$
0)
#130000
1$
1)
#135000
0$
0)
#140000
1$
1)
#145000
0$
0)
#150000
1$
1)
#155000
0$
0)
#160000
0!
1"
1#
18
19
b0 4
b1011 5
b1011 ?
b1101 6
b1101 C
b1000 F
b0 >
b1000 :
b1000 <
b0 A
b1000 B
b0 E
b0 3
1$
1)
b11 '
b11 ,
b11 7
b11 =
b11 @
b11 D
b11 (
b11 -
b11 0
b11 2
b101 %
b101 *
b101 .
#165000
0"
0#
0$
0)
#170000
1"
1#
1$
1)
#175000
0"
0#
0$
0)
#180000
1"
1#
1$
1)
#185000
0"
0#
0$
0)
#190000
1"
1#
1$
1)
#195000
0"
0#
0$
0)
#200000
1"
1#
1$
1)
